jsonapi_mock_server/__init__.py
jsonapi_mock_server/base_metadata.py
jsonapi_mock_server/base_models.py
jsonapi_mock_server/base_tests.py
jsonapi_mock_server/base_views.py
jsonapi_mock_server/fake.py
jsonapi_mock_server/hooks.py
jsonapi_mock_server/json_api_builder.py
jsonapi_mock_server/utils.py
jsonapi_mock_server/tests/__init__.py
jsonapi_mock_server/tests/test_hooks.py
jsonapi_mock_server/tests/test_json_api_builder.py
jsonapi_mock_server-0.15.dist-info/DESCRIPTION.rst
jsonapi_mock_server-0.15.dist-info/METADATA
jsonapi_mock_server-0.15.dist-info/RECORD
jsonapi_mock_server-0.15.dist-info/WHEEL
jsonapi_mock_server-0.15.dist-info/metadata.json
jsonapi_mock_server-0.15.dist-info/top_level.txt
