Metadata-Version: 2.0
Name: jsonapi-mock-server
Version: 0.15
Summary: JSON API mock server
Home-page: https://github.com/ZeroCater/jsonapi-mock-server
Author: ZeroCater
Author-email: UNKNOWN
License: MIT
Keywords: jsonapi mock server
Platform: UNKNOWN
Classifier: Development Status :: 3 - Alpha
Classifier: Environment :: Web Environment
Classifier: Framework :: Django
Classifier: Intended Audience :: Developers
Classifier: License :: OSI Approved :: MIT License
Classifier: Operating System :: OS Independent
Classifier: Programming Language :: Python
Classifier: Programming Language :: Python :: 2
Classifier: Programming Language :: Python :: 2.7
Classifier: Topic :: Internet :: WWW/HTTP
Classifier: Topic :: Software Development :: Libraries :: Application Frameworks
Classifier: Topic :: Software Development :: Libraries :: Python Modules
Requires-Dist: django (<2,>=1.7)
Requires-Dist: django-cors-headers
Requires-Dist: djangorestframework
Requires-Dist: faker
Requires-Dist: inflection
Requires-Dist: jsondiff
Requires-Dist: requests
Requires-Dist: simplejson
Requires-Dist: urllib3[secure]
